{
  "refreshed_at_utc": "2026-05-13T19:40:43.712661+00:00",
  "run_id": "90a793e2bf0f",
  "thresholds": {
    "tiers": {
      "high": 0.85,
      "medium": 0.7,
      "low": 0.5
    },
    "evm": {
      "cpi_warn": 0.9,
      "spi_warn": 0.9
    },
    "quality": {
      "min_numeric_pct": 60,
      "min_input_rows": 5
    }
  },
  "inputs": [
    "P018 - P01 Airport Carpark.xlsx",
    "P019 - P02 Landfill Cell.xlsx",
    "P020 - P03 Regional Bypass Road.xlsx",
    "P021 - P04 Regional Arterial Pavement Repairs.xlsx",
    "P022 - P05 Semi-Urban Road Reconstruction.xlsx",
    "P024 - P06 Urban Road Reconstruction.xlsx"
  ],
  "scores_rows": 6,
  "alerts_rows": 11,
  "versions": {
    "python": "3.12.8",
    "platform": "Windows-10-10.0.19045-SP0",
    "pandas": "2.3.3",
    "numpy": "2.0.2"
  },
  "config_hash": "404be368774e1cf715ab9dcdbc060a58e647168d231136e1d92376585b53d3cb"
}